alibabacloud_eiam_developerapi20220225/__init__.py
alibabacloud_eiam_developerapi20220225/client.py
alibabacloud_eiam_developerapi20220225/models/__init__.py
alibabacloud_eiam_developerapi20220225/models/_add_user_to_organizational_units_headers.py
alibabacloud_eiam_developerapi20220225/models/_add_user_to_organizational_units_request.py
alibabacloud_eiam_developerapi20220225/models/_add_user_to_organizational_units_response.py
alibabacloud_eiam_developerapi20220225/models/_add_users_to_group_headers.py
alibabacloud_eiam_developerapi20220225/models/_add_users_to_group_request.py
alibabacloud_eiam_developerapi20220225/models/_add_users_to_group_response.py
alibabacloud_eiam_developerapi20220225/models/_create_group_headers.py
alibabacloud_eiam_developerapi20220225/models/_create_group_request.py
alibabacloud_eiam_developerapi20220225/models/_create_group_response.py
alibabacloud_eiam_developerapi20220225/models/_create_group_response_body.py
alibabacloud_eiam_developerapi20220225/models/_create_organizational_unit_headers.py
alibabacloud_eiam_developerapi20220225/models/_create_organizational_unit_request.py
alibabacloud_eiam_developerapi20220225/models/_create_organizational_unit_response.py
alibabacloud_eiam_developerapi20220225/models/_create_organizational_unit_response_body.py
alibabacloud_eiam_developerapi20220225/models/_create_user_headers.py
alibabacloud_eiam_developerapi20220225/models/_create_user_request.py
alibabacloud_eiam_developerapi20220225/models/_create_user_response.py
alibabacloud_eiam_developerapi20220225/models/_create_user_response_body.py
alibabacloud_eiam_developerapi20220225/models/_delete_group_headers.py
alibabacloud_eiam_developerapi20220225/models/_delete_group_response.py
alibabacloud_eiam_developerapi20220225/models/_delete_organizational_unit_headers.py
alibabacloud_eiam_developerapi20220225/models/_delete_organizational_unit_response.py
alibabacloud_eiam_developerapi20220225/models/_delete_user_headers.py
alibabacloud_eiam_developerapi20220225-1.2.0.dist-info/LICENSE
alibabacloud_eiam_developerapi20220225-1.2.0.dist-info/METADATA
alibabacloud_eiam_developerapi20220225-1.2.0.dist-info/WHEEL
alibabacloud_eiam_developerapi20220225-1.2.0.dist-info/top_level.txt
alibabacloud_eiam_developerapi20220225-1.2.0.dist-info/RECORD
